pro_logging/__init__.py
pro_logging/logger.py
pro_logging-1.0.0.dist-info/METADATA
pro_logging-1.0.0.dist-info/WHEEL
pro_logging-1.0.0.dist-info/top_level.txt
pro_logging-1.0.0.dist-info/RECORD
