Metadata-Version: 2.1
Name: pro-logging
Version: 1.0.0
Summary: An advanced logging package for Python projects
Home-page: https://github.com/mjavadhe/arduinopy
Author: Mohamadjavad Heydarpanah
Author-email: mjavad.heydarpanah@gmail.com
Classifier: Programming Language :: Python :: 3
Classifier: Operating System :: OS Independent
Requires-Python: >=3.6
